MANIFEST.in
README.rst
setup.py
docs/HISTORY.txt
docs/INSTALL.txt
docs/LICENSE.GPL
docs/LICENSE.txt
redturtle/__init__.py
redturtle.alternative_orderui.egg-info/PKG-INFO
redturtle.alternative_orderui.egg-info/SOURCES.txt
redturtle.alternative_orderui.egg-info/dependency_links.txt
redturtle.alternative_orderui.egg-info/entry_points.txt
redturtle.alternative_orderui.egg-info/namespace_packages.txt
redturtle.alternative_orderui.egg-info/not-zip-safe
redturtle.alternative_orderui.egg-info/requires.txt
redturtle.alternative_orderui.egg-info/top_level.txt
redturtle/alternative_orderui/__init__.py
redturtle/alternative_orderui/configure.zcml
redturtle/alternative_orderui/interfaces.py
redturtle/alternative_orderui/tests.py
redturtle/alternative_orderui/Extensions/install.py
redturtle/alternative_orderui/browser/__init__.py
redturtle/alternative_orderui/browser/arrow-move_16x16.gif
redturtle/alternative_orderui/browser/configure.zcml
redturtle/alternative_orderui/browser/nokss_order.kss
redturtle/alternative_orderui/browser/ordersupportui.js
redturtle/alternative_orderui/profiles/default/browserlayer.xml
redturtle/alternative_orderui/profiles/default/jsregistry.xml
redturtle/alternative_orderui/profiles/default/kssregistry.xml
redturtle/alternative_orderui/profiles/default/metadata.xml
redturtle/alternative_orderui/profiles/default/skins.xml
redturtle/alternative_orderui/profiles/uninstall/browserlayer.xml
redturtle/alternative_orderui/profiles/uninstall/jsregistry.xml
redturtle/alternative_orderui/profiles/uninstall/kssregistry.xml
redturtle/alternative_orderui/profiles/uninstall/skins.xml
redturtle/alternative_orderui/skins/alternative_orderui/folder_position.cpy
redturtle/alternative_orderui/skins/alternative_orderui/folder_position.cpy.metadata