Metadata-Version: 1.1
Name: redturtle.alternative-orderui
Version: 0.5.0
Summary: An alternative order UI support for contents view in Plone
Home-page: http://plone.org/products/redturtle.alternative_orderui
Author: RedTurtle Technology
Author-email: sviluppoplone@redturtle.net
License: GPL
Keywords: plone plonegov folder_contents order
Platform: UNKNOWN
Classifier: Framework :: Plone
Classifier: Programming Language :: Python
Classifier: Programming Language :: JavaScript
Classifier: Topic :: Software Development :: Libraries :: Python Modules
Classifier: Development Status :: 5 - Production/Stable
